README.md
setup.py
neptune_resolver_rest/__init__.py
neptune_resolver_rest/connect.py
neptune_resolver_rest/resolver.py
neptune_resolver_rest.egg-info/PKG-INFO
neptune_resolver_rest.egg-info/SOURCES.txt
neptune_resolver_rest.egg-info/dependency_links.txt
neptune_resolver_rest.egg-info/requires.txt
neptune_resolver_rest.egg-info/top_level.txt